p5/__init__.py
p5/__main__.py
p5/__version__.py
p5/core/__init__.py
p5/core/api.py
p5/core/attribs.py
p5/core/color.py
p5/core/constants.py
p5/core/font.py
p5/core/geometry.py
p5/core/graphics.py
p5/core/image.py
p5/core/light.py
p5/core/material.py
p5/core/p5.py
p5/core/primitives.py
p5/core/primitives3d.py
p5/core/structure.py
p5/core/svg.py
p5/core/tess.py
p5/core/transforms.py
p5/core/vertex.py
p5/core/tests/__init__.py
p5/core/tests/test_color.py
p5/core/tests/test_geometry.py
p5/core/tests/test_shape.py
p5/core/tests/test_svg.py
p5/data/__init__.py
p5/data/api.py
p5/data/local_storage.py
p5/io/__init__.py
p5/io/api.py
p5/io/http_data.py
p5/io/local_data.py
p5/p5types/__init__.py
p5/pmath/__init__.py
p5/pmath/api.py
p5/pmath/curves.py
p5/pmath/matrix.py
p5/pmath/rand.py
p5/pmath/time.py
p5/pmath/utils.py
p5/pmath/vector.py
p5/pmath/tests/__init__.py
p5/pmath/tests/test_curves.py
p5/pmath/tests/test_matrix.py
p5/pmath/tests/test_utils.py
p5/pmath/tests/test_vector.py
p5/sketch/__init__.py
p5/sketch/api.py
p5/sketch/events.py
p5/sketch/userspace.py
p5/sketch/util.py
p5/sketch/Skia2DRenderer/__init__.py
p5/sketch/Skia2DRenderer/base.py
p5/sketch/Skia2DRenderer/graphics.py
p5/sketch/Skia2DRenderer/handlers.py
p5/sketch/Skia2DRenderer/image.py
p5/sketch/Skia2DRenderer/renderer2d.py
p5/sketch/Skia2DRenderer/util.py
p5/sketch/Vispy2DRenderer/__init__.py
p5/sketch/Vispy2DRenderer/base.py
p5/sketch/Vispy2DRenderer/image.py
p5/sketch/Vispy2DRenderer/openglrenderer.py
p5/sketch/Vispy2DRenderer/renderer2d.py
p5/sketch/Vispy2DRenderer/shaders2d.py
p5/sketch/Vispy2DRenderer/shape.py
p5/sketch/Vispy2DRenderer/shaders/2d/default2d.vert
p5/sketch/Vispy2DRenderer/shaders/2d/stroke.frag
p5/sketch/Vispy2DRenderer/shaders/2d/stroke.vert
p5/sketch/Vispy2DRenderer/shaders/2d/texture.frag
p5/sketch/Vispy2DRenderer/shaders/2d/texture.vert
p5/sketch/Vispy2DRenderer/shaders/common/default.frag
p5/sketch/Vispy2DRenderer/shaders/common/fbuffer.frag
p5-0.8.4.dist-info/LICENSE
p5-0.8.4.dist-info/METADATA
p5-0.8.4.dist-info/WHEEL
p5-0.8.4.dist-info/top_level.txt
p5-0.8.4.dist-info/RECORD
