Metadata-Version: 2.1
Name: p5
Version: 0.8.4
Summary: Creative coding in Python
Home-page: https://p5py.github.io
Author: Abhik Pal
Author-email: theabhikpal@gmail.com
License:  GNU GPLv3
Classifier: Development Status :: 3 - Alpha
Classifier: Intended Audience :: Developers
Classifier: Intended Audience :: Education
Classifier: Topic :: Artistic Software
Classifier: Topic :: Education
Classifier: Topic :: Multimedia
Classifier: Topic :: Multimedia :: Graphics
Classifier: License :: OSI Approved :: GNU General Public License v3 (GPLv3)
Classifier: Programming Language :: Python :: 3
Classifier: Programming Language :: Python :: 3.7
Classifier: Programming Language :: Python :: 3.8
Classifier: Programming Language :: Python :: 3.9
Classifier: Programming Language :: Python :: 3.10
Classifier: Programming Language :: Python :: 3.11
Requires-Python: >=3.7
License-File: LICENSE
Requires-Dist: glfw>=2.5.9
Requires-Dist: numpy
Requires-Dist: Pillow==9.0.1
Requires-Dist: vispy==0.10.0
Requires-Dist: PyOpenGL-accelerate==3.1.7
Requires-Dist: PyOpenGL==3.1.6
Requires-Dist: requests>=2.25.0
Requires-Dist: dataclasses; python_version == "3.6"
Requires-Dist: skia-python>=85.0
